{
 "id": "I-O",
 "partie": "I",
 "rubrique": "O",
 "title": "Décret du 12 mars 1975 réglementant l'exploitation des établissements touristiques.",
 "number": "Décret du 12 mars 1975",
 "moniteurRef": "Le Moniteur n° 32 du 21 avril 1975",
 "publicationDate": "1975-04-21",
 "body": "Chapitre premier — Définition et énumération\nArticle 1er.- Toute personne, habile à exercer le commerce, peut être exploitante d'un établissement touristique moyennant qu'elle observe les prescriptions du présent décret.\nL'établissement touristique s'entend de toute entreprise qui bénéficie d'une licence d'exploitation, émanée de l'ONTRP et qui offre à une clientèle de touristes, l'hébergement, la nourriture, la boisson et les loisirs. Ainsi sont désignés, sous ce titre, les hôtels, motels, villages de vacances, bars, restaurants aménagés à cette fin.\nPourront également bénéficier de cette licence et jouir des avantages attachés aux établissements touristiques:\na) les galeries d'art et les maisons de commerce spécialisées dans la vente d'ouvrages sélectionnés de vannerie, de broderie, de peinture, de tapisserie, ainsi que des articles de petites industries locales, destinés particulièrement aux touristes.\nb) les plages et stations balnéaires réunissant les conditions ci-dessous stipulées.\nLa construction, la transformation, l'organisation, l'aménagement ou l'ouverture de ces établissements, ainsi que leur gestion ou exploitation demeurant soumis à la présente législation pour ce qui concerne leurs rapports avec l'Office National du Tourisme et des Relations Publiques, désigné sous la rubrique «ONTRP».\nChapitre II — Des formalités préliminaires\nArticle 2.- Quiconque désire construire, ouvrir, exploiter un établissement touristique, devra, avant d'en commencer l'exploitation, se conformer aux conditions et obligations suivantes:\n1°) Présenter à l'ONTRP une requête claire et précise, laquelle exposera le projet et sera accompagnée au besoin des données de ces possibilités économiques et financières ou de tous autres renseignements capables d'édifier sur le succès éventuel de la réalisation de ce projet. L'office, s'il trouve les éléments concluants, pourra émettre en faveur du requérant une approbation, dite «Approbation de Première Étape».\n2°) Soumettre, sitôt l'obtention de cette approbation, les documents et plans en vue de leur examen dans un délai de 2 mois par le Service Technique de l'ONTRP qui, sur rapport favorable, accordera l'autorisation requise.\n3°) Accepter, durant la phase de la réalisation ou de la marche des travaux, le contrôle des agents qualifiés de l'ONTRP et mettre en exécution toutes les suggestions convenues entre l'Office et le bénéficiaire de l'autorisation.\n4°) Donner avis à l'ONTRP de la date d'achèvement des travaux ou de la réalisation du projet qui doit être conforme aux plans et modifications dûment approuvés par l'office. Dans ce cas, après contrôle et rapport des agents compétents, la Direction Générale de l'Office délivrera au requérant un certificat, dit «Certificat de Conformité», l'habilitant à solliciter la licence d'exploitation.\nArticle 3.- Les travaux convenus doivent être entrepris dans un délai de deux années à partir de l'autorisation, sous peine d'invalidité de ladite autorisation.\nArticle 4.- L'approbation des plans par l'ONTRP ne dispense pas l'intéressé d'obtenir tous les permis et licences prévus par les lois et règlements en vigueur, ni ne s'oppose à ce que l'ONTRP, en cas de conflits intervenus à la phase de réalisation, suspende ou rétracte l'autorisation octroyée.\nArticle 5.- La demande d'autorisation sera considérée comme rejetée, s'il s'est écoulé trois mois sans que cette autorisation ait été délivrée par l'ONTRP. Elle pourra être reproduite dans la même forme sous la diligence du requérant. Il en sera de même en cas d'invalidité de l'autorisation.\nChapitre III — De la licence d'exploitation\nArticle 6.- La licence ne sera émise que sur requête expresse de l'intéressé, adressée à la Direction Générale de l'ONTRP, deux mois au moins avant l'ouverture de l'établissement.\nCette requête contiendra une description détaillée de l'installation. Y seront annexés les documents suivants:\n1°) Un extrait de l'état civil, attestant que le requérant est haïtien et majeur.\n2°) Un certificat de bonne vie et mœurs, délivré par l'Administration communale et visé par le juge de paix et par la police.\n3°) Un acte établissant que le propriétaire de l'entreprise ou la personne responsable de la gestion possède la qualification technique et professionnelle nécessaire à ce genre d'activité, en tenant compte de l'importance de l'installation.\n4°) Un acte justifiant que l'établissement est immatriculé au Département du Commerce et indiquant le capital exposé, le type d'établissement ainsi que sa dénomination.\n5°) Une pièce établissant, s'il s'agit d'une société, que cette dernière a un statut légal en Haïti, la soumettant ainsi aux lois et règlements en vigueur.\n6°) La photocopie du certificat de conformité à défaut de la pièce originale.\n7°) Un acte de bail en bonne et due forme, si l'exploitant est locataire ou un titre de propriété s'il est propriétaire.\nSi le requérant est une personne physique ou morale étrangère, il soumettra, en lieu et place de l'extrait d'état civil et du certificat de bonne vie et mœurs, tout document émané du consulat de son pays, ou d'un notaire de son domicile ou du siège social de la société pouvant justifier sa nationalité, sa moralité, sa capacité ou son statut personnel.\nArticle 7.- Après étude de ce dossier, accomplissement du contrôle et des inspections nécessaires et l'avis de la commission consultative du Conseil National du Tourisme, la Direction Générale de l'ONTRP accordera la «licence d'exploitation».\nCette licence est personnelle au bénéficiaire et ne pourra être cédée ou transférée à toute personne qu'avec l'accord de l'ONTRP. De même, l'approbation de l'Office est nécessaire, une fois la licence émise, pour toute substitution de personne ou l'admission à l'établissement d'un nouvel associé ou d'un directeur responsable.\nArticle 8.- Dans le cas où l'ensemble des travaux ne serait pas observé, si la partie exécutée remplit toutes les conditions requises pour le fonctionnement, l'intéressé pourra obtenir une licence provisoire pour l'exploitation de cette partie. Il soumettra, avec sa réquisition de fonctionnement, un certificat du Département de la Santé Publique et de la Population, attestant que la portion achevée répond aux exigences de l'hygiène et de la sécurité publique.\nPareille licence ne sera accordée que pour une durée d'une année en attendant l'achèvement de l'ensemble.\nArticle 9.- La «licence d'exploitation» est émise sous forme de lettre officielle, scellée et signée du Directeur Général de l'ONTRP, ou, en son absence, de son représentant.\nArticle 10.- Les étrangers ne pourront bénéficier de cette licence que s'ils remplissent toutes les conditions prévues par les lois haïtiennes.\nArticle 11.- Les modifications et changements à apporter soit à l'installation, soit au statut de l'établissement devront être notifiés à l'ONTRP un mois au moins avant leur réalisation. Dans ce cas, l'exploitant annexera à sa requête tous les documents nécessaires en vue de l'agrément de ces transformations.\nChapitre IV — Des avantages\nArticle 12.- Toute personne autorisée à exploiter un établissement touristique pourra bénéficier des avantages qui suivent:\n1°) La franchise douanière accordée par l'État à tout promoteur d'industrie nouvelle en ce qui concerne les articles introuvables dans le pays et nécessaires à l'installation, compte tenu de l'observance des conditions et formalités prévues par la loi y relative.\n2°) La concession ou la location de terrains domaniaux, si le projet soumis a reçu l'agrément de l'Office.\n3°) L'assistance des agents de l'ONTRP ou le concours du Tourisme pour faciliter la solution de tous différends avec les services publics haïtiens, qu'il s'agisse de difficultés rencontrées par le requérant à la phase d'exécution du projet ou par l'exploitant durant le fonctionnement.\nArticle 13.- S'agissant de concession ou de location, de terrains domaniaux, des options d'une durée d'une année pourront être accordées aux promoteurs afin de leur permettre d'établir leur projet et d'en obtenir l'agrément.\nCet agrément ne dispense pas les bénéficiaires des autorisations et formalités imposées par les lois et règlements en vigueur, notamment le permis de construire.\nArticle 14.- Pour bénéficier de l'assistance des agents de l'ONTRP et du concours de l'Office, l'intéressé devra les solliciter par lettre avec mention d'urgence, adressée à la Direction Générale en ayant soin d'indiquer la nature du différend ou des difficultés.\nL'Office conserve le droit de ne pas s'y intéresser, s'il le juge nécessaire.\nChapitre V — Du fonctionnement\nArticle 15.- Les établissements touristiques, munis de la licence d'exploitation afficheront à leur porte principale d'entrée ou dans leur salle d'accueil:\na) une photocopie de cette licence.\nb) un extrait des dispositions réglementaires relatives aux conditions d'admission à ces établissements et à leurs responsabilités.\nIls tiendront également les registres nécessaires à leur fonctionnement, lesquels seront tenus à jour pour pouvoir répondre, en cas d'infraction ou de poursuite, à toute réquisition des agents contrôleurs de l'ONTRP ou de tous autres organismes d'État préposés par la loi à cet effet.\nIls enverront chaque mois à l'ONTRP et pareillement sur sa demande, les statistiques, renseignements et rapports intéressant le tourisme en utilisant les formes établies par l'Office.\nArticle 16.- Aucun établissement n'est autorisé à prendre un nom ou une dénomination, s'il n'a pas obtenu l'accord préalable de l'Office.\nCette dénomination ne peut être utilisée que pour un seul établissement de quelque catégorie qu'il soit, à moins qu'il ne s'agisse d'un même exploitant.\nLe nom et le numéro de la licence seront mentionnés sur tout imprimé officiel de l'établissement.\nAucune entreprise n'est autorisée à se servir d'une dénomination qui ne lui a pas été consentie par l'ONTRP.\nChapitre VI — Du classement et des prix — A.- Du classement\nArticle 17.- Les établissements touristiques sont classés par type et catégorie dans les conditions qui seront déterminées par arrêté.\nUn panonceau placé à l'entrée de l'établissement comportera un signe distinctif et en indiquera la classe.\nArticle 18.- Les hôtels, motels et restaurants pourront être classés en une ou plusieurs catégories fournissant tout ou une partie des prestations habituellement servies par l'industrie hôtelière. La qualité de ces prestations doit être suffisante pour que l'établissement reçoive une clientèle touristique.\nLes classements arrêtés par l'ONTRP s'imposent à tous. Aucun document de publicité touristique ne doit contenir d'indication de nature à créer une équivoque à cet égard.\nArticle 19.- La qualité d'établissement touristique n'est reconnue que, soit sur leur demande, soit même d'office par l'ONTRP, aux seules entreprises dont l'installation présente des caractéristiques de confort précisées par le susdit arrêté et dont l'exploitation est assurée dans des conditions satisfaisantes de moralité et de compétence professionnelle.\nArticle 20.- Nul ne peut distribuer aux établissements relevant de l'industrie hôtelière des panonceaux ou insignes publicitaires sans l'autorisation de l'ONTRP.\nNotamment, il est interdit d'apposer à l'extérieur desdits établissements et dans les dépendances accessibles au public, des panonceaux ou insignes publicitaires dont la distribution n'a pas été autorisée.\nB.- Des prix\nArticle 21.- Une fois par an, les exploitants de tous établissements touristiques doivent présenter, sous pli recommandé à l'ONTRP, les listes détaillées des prix qu'ils entendent appliquer dans leurs établissements durant la saison prochaine, ce, au cours du mois de juin. Passé ce délai, l'exploitant devra conserver les prix de l'année précédente.\nCes prix qui doivent comprendre les taxes et les services sont mentionnés, le cas échéant, pour les deux périodes de «haute saison» et de «basse saison» dont la durée devra être précisée.\nSeront déclarés distinctement les prix:\n1°) De location des chambres à une ou à deux personnes; De location des chambres à eau courante chaude ou froide; De location des chambres avec cabinet de toilette; De location des chambres avec cabinet de toilette et W.C.; De location des chambres avec salle de bain ou de douche.\n2°) Des petits déjeuners.\nArticle 22.- Le service compétent de l'ONTRP étudie les listes de prix. S'il les approuve, ces listes sont applicables; mais si les points de vue de l'exploitant et de l'administration ne concordent pas, la question sera transmise à la Commission Consultative du Conseil National du Tourisme pour son avis.\nArticle 23.- Les nouveaux prix entreront en vigueur dès leur approbation par l'ONTRP.\nAucun changement ne peut y être effectué sans l'approbation de l'Office; la liste arrêtée demeure valable tant qu'il n'y a eu aucun amendement.\nArticle 24.- Les établissements relevant de l'industrie hôtelière ne peuvent opérer aucune réduction de leurs prix au-dessous de 40 %. Tous établissements qui pratiqueraient des prix inférieurs à ceux approuvés par l'ONTRP, seront reconsidérés quant à leur classement et placés dans la catégorie inférieure correspondant aux prix pratiqués.\nArticle 25.- Dans ces cas spéciaux d'extrême nécessité, l'exploitant pourra solliciter une modification des prix. L'ONTRP, touché de cette demande, prendra l'avis du Département du Commerce sur le bien-fondé de l'augmentation ou de la diminution.\nArticle 26.- Sitôt l'approbation des prix par l'ONTRP, l'exploitant sera tenu de les afficher dans un lieu saillant de l'établissement et à la porte des chambres de façon à ce qu'il soit facile aux clients, de prendre connaissance de leurs détails en toute clarté.\nArticle 27.- Les exploitants des bars et restaurants de tourisme sont tenus de publier les prix de façon claire permettant aux clients de les voir et les lire.\nArticle 28.- Les listes de prix sont rédigées et publiées, en anglais et en espagnol, en gourdes et en dollars.\nArticle 29.- Les établissements qui organisent des galas spéciaux peuvent percevoir un droit d'entrée ou des prix de commande extra, ce, après soumission des programmes à présenter et des motifs justifiant la perception de ce droit et de ces prix exceptionnels en vue de l'approbation de l'ONTRP.\nArticle 30.- Les comptes des exploitants seront précis et seront présentés aux clients avec inclusion des renseignements suivants:\n1°) Les prix perçus\n2°) Le nombre des séjours quotidiens, pour les établissements d'hébergement\n3°) Le coût des diverses prestations indiquées séparément.\nLes factures numérotées seront soumises aux clients. Elles comprendront ce qui a été consommé en détail.\nLa Direction de l'établissement est responsable de la régularité de son contenu. Il sera procédé à la vérification de ces registres et documents par l'ONTRP, sur demande du chef de service compétent.\nC.- Du déclassement\nArticle 31.- Le déclassement d'un établissement touristique est prononcé dans le cas de non-conformité aux caractéristiques de sa catégorie ou de l'inobservance des prix arrêtés. Il pourra être également prononcé pour défaut ou insuffisance grave d'entretien de l'immeuble et des installations et, d'une façon générale, lorsque l'exploitation cesse d'être assurée dans des conditions d'accueil, de moralité et de compétence professionnelle.\nLe déclassement est prononcé par l'ONTRP après avis de la Commission Consultative du Conseil National du Tourisme. En cas de déclassement, l'exploitant, dès notification de la décision, est tenu de remplacer le panonceau par un autre correspondant à la nouvelle catégorie de l'établissement.\nChapitre VII — Des conditions d'exploitation hôtelière\nArticle 32.- Le contrat est conclu entre l'exploitant et les clients lorsque l'accord est réalisé sur les conditions de l'admission.\nLa base du contrat est l'information du client au sujet des règlements spéciaux à l'établissement et des prix de son hébergement, et des prestations diverses.\nArticle 33.- Le voyageur jouit, dès la conclusion du contrat, des droits suivants:\n1.- l'utilisation de la chambre qui lui est affectée;\n2.- la jouissance des moyens de confort et des équipements hôteliers et touristiques affectés à l'usage des passagers;\n3.- le service ordinaire.\nArticle 34.- Le voyageur doit être informé des conditions qui suivent:\n1°) les dispositions du contrat conclu entre lui et l'exploitant n'ont d'effet qu'à l'égard des parties;\n2°) le voyageur ne peut louer, occuper et faire occuper la chambre qu'en vertu d'un accord avec la direction de l'établissement;\n3°) le voyageur qui accepte la chambre, la nourriture, le logement et autres services assurés par l'établissement sans être fixé sur les prix, demeure soumis à ceux pratiqués par l'établissement;\n4°) le voyageur est responsable de tout dommage qui se produit dans l'établissement, résultant de son fait;\n5°) l'utilisation du courant électrique à d'autres fins que l'éclairage, ainsi que celle des autres équipements, restent soumises au règlement intérieur de l'établissement; elles feront l'objet d'accord spécial;\n6°) le client ne peut y introduire des animaux sans entente préalable avec la direction. L'entrée des animaux aux salles publiques, notamment à la salle à manger, est interdite;\n7°) l'usage des appareils de musique et les réunions de toutes sortes, de nature à produire du bruit et à troubler la tranquillité de l'hôtel, le repos des hôtes, ne peuvent être autorisés que dans certaines limites et à des heures déterminées. Ils seront interdits, en cas de contravention. L'inobservance par le voyageur, informé de ces conditions, autorise l'exploitant à résilier immédiatement le contrat.\nArticle 35.- Toute demande de réservation de chambre produite par le voyageur et agréée par la direction d'un établissement lie les parties. Elle doit toujours porter indication des prestations à fournir. Elle entraîne pour le client l'obligation d'accepter les chambres qui lui ont été réservées, pourvu qu'elles soient conformes à sa réquisition et à son désir et, en cas de refus, celle d'indemniser l'exploitant. Cette indemnité doit représenter le gain réel dont ce dernier a été privé.\nDe son côté, l'exploitant qui a agréé la demande est tenu de loger le client, à défaut de place en son établissement, dans un autre offrant des conditions correspondantes quant à la classe, aux prix et à la situation.\nArticle 36.- L'exploitant prépare la note sur la base suivante:\n1°) Les prix du logement sont calculés normalement pour un jour complet ou une nuitée, soit une durée de 24 heures.\n2°) Le séjour est calculé par jour, à compter de la date et de l'heure d'arrivée.\n3°) Toute fraction de jour est considérée pour un jour sauf accord préalable entre le voyageur et la direction de l'établissement.\nArticle 37.- Si un client quitte l'établissement avant la fin de la période convenue, la direction, sauf cas de force majeure, peut lui réclamer un dédommagement pour le préjudice réel qu'elle a subi de ce fait. Au cas où avis lui a été donné 24 heures avant le départ, il ne sera perçu que le loyer d'une journée.\nArticle 38.- Lorsqu'un voyageur réserve une chambre pour une période déterminée et qu'au cours de cette période, la chambre a été louée à une autre personne, l'exploitant est tenu de l'évacuer immédiatement et de la livrer à celui qui en avait fait la réservation.\nArticle 39.- Le voyageur qui a réservé une chambre pour une période déterminée, est tenu de l'évacuer à l'expiration de cette période sauf entente avec la direction. S'il refuse de le faire, il est tenu aux dommages-intérêts ainsi qu'à l'évacuation immédiate.\nArticle 40.- L'accord pour une période déterminée, doit être fait sur la base du tarif en vigueur. Il peut concerner soit le logement et la nourriture, soit l'un ou l'autre.\nArticle 41.- En cas de non-paiement de la chambre ou des prestations diverses, l'exploitant a le droit de porter plainte au Parquet et à l'ONTRP. Il peut également retenir les bagages du voyageur en vue de percevoir les montants dus, sous réserve d'en informer ces deux organismes.\nArticle 42.- Est passible de poursuites pour abus de confiance toute personne qui se fait héberger ou qui consomme de la nourriture ou des boissons dans un établissement touristique, sachant qu'elle n'est pas en mesure de payer.\nArticle 43.- Les objets perdus, trouvés dans l'établissement seront remis à la direction aux fins de droit.\nArticle 44.- Les factures doivent être acquittées dès leur réception. Toutes les dépenses de renseignements, de télégrammes, de commissions bancaires, de différences de changes et autres restent à la charge du client.\nArticle 45.- À la fin de chaque semaine, la direction remettra aux clients la facture des montants qu'ils doivent à l'établissement.\nArticle 46.- La direction de l'établissement est tenue d'assurer l'acheminement des correspondances parvenues aux clients après leur départ, au cas où ces derniers laisseraient leurs nouvelles adresses.\nSi l'exploitant ignore le domicile du destinataire, il doit refuser de recevoir la lettre. Dans ce cas, l'administration postale le retournera à son expéditeur.\nArticle 47.- L'exploitant et ses employés qualifiés peuvent pénétrer dans les chambres louées au moyen de la double clé ou de la «clé passe-partout» en vue du nettoyage et de l'aménagement. Ils sont tenus de ne pas déranger le voyageur et d'en respecter le repos.\nArticle 48.- Toute déclaration de convention visant à exclure ou à limiter les responsabilités des parties est nulle et sans effet.\nChapitre VIII — Des contrats hôteliers par intermédiaires ou agents de voyages\nArticle 49.- Tout contrat hôtelier, émané d'un agent ou intermédiaire de voyage, doit être précédé d'une demande de réservation qui portera indication des prestations à fournir ainsi que de la contre-valeur de celles-ci. Ce contrat ne deviendra définitif que par l'acceptation de la demande.\nEn ce cas, les prix des services commandés doivent consister en un document écrit (lettre, télégramme, télex, ordinateur, etc.).\nSi l'agent de voyage exige une réponse télégraphique, il sera tenu d'utiliser la formule de «réponse payée».\nArticle 50.- Les prix notifiés à l'agent de voyage pour les services demandés, ne seront en aucun cas, supérieurs à ceux du tarif d'hôtel à l'usage des clients directs, peu importe que la facture soit payée par l'agent de voyage ou directement par le voyageur.\nArticle 51.- Les prestations à payer sont celles qui figurent sur sa demande de réservation.\nArticle 52.- Dans le cas de facture payée directement par le voyageur, l'agent de voyage qui a conclu le contrat demeurera le débiteur de la facture.\nArticle 53.- Le règlement de la facture aura lieu dans les délais convenus ou, à défaut de stipulation contractuelle, dans les délais normaux.\nArticle 54.- L'agent de voyage pourra être requis de payer la note d'hôtel, moins les commissions, avant ou pendant le séjour du voyageur.\nArticle 55.- L'établissement pourra subordonner l'acceptation de la réservation au versement d'un montant préalable, lequel aura le caractère d'un dépôt de garantie. Dans ce cas, le contrat ne sera réputé conclu qu'au moment où le versement aura été effectué ou la preuve du versement produite.\nArticle 56.- L'hôtelier devra accuser réception de tout versement préalable, au plus tard 24 heures après.\nArticle 57.- Le montant du versement préalable habituel est égal au prix des services commandés (logement, repas, etc.) pour un séjour d'une nuitée en «basse saison» et de trois en «haute saison».\nArticle 58.- Tout contrat hôtelier donne lieu en faveur de l'agent de voyage, au paiement d'un pourcentage sur le prix des services fournis durant le séjour.\nCette commission est également due pour toute prolongation de séjour, c'est-à-dire toute nouvelle occupation des lieux par le voyageur durant un même voyage.\nArticle 59.- Aucune commission ne pourra être due, pour le même voyageur, au-delà d'un hébergement de trente jours.\nLa commission sera de 10 % sur le prix des prestations. Ce taux est maximum.\nArticle 60.- L'hôtelier paiera par prélèvement, le montant de la commission due à l'agent de voyage, en le déduisant de sa facture.\nSi la facture doit être payée directement par le voyageur à l'hôtelier, ce dernier versera la commission dans un délai qui ne pourra excéder 30 jours, sauf accord avec l'agent de voyage.\nArticle 61.- Toute annulation de la réservation doit être faite dans la forme utilisée pour la demande de réservation produite par l'agent de voyage.\nElle peut être totale ou partielle. Pour qu'elle n'entraîne pas d'indemnité en faveur de l'établissement, elle doit être notifiée à temps, 15 jours au moins avant la date fixée pour l'arrivée des voyageurs.\nArticle 62.- En dehors de ces dispositions spéciales, le contrat hôtelier reste régi par les dispositions générales et par celles applicables à un client direct.\nChapitre IX — Du contrôle des établissements touristiques\nArticle 63.- Le contrôle des établissements touristiques en ce qui concerne l'application des dispositions du présent décret et des règlements, la tenue desdits établissements, la qualité du service et de l'accueil et autres, sera assuré par des agents spécialement nommés à cet effet.\nCes fonctionnaires prêteront serment par-devant le juge de paix avant d'entrer en charge et auront le rôle d'agent de police judiciaire attaché à l'Office.\nArticle 64.- La commission de contrôle, par ses agents, procèdera, sur l'ordre de l'administration supérieure, à la visite des établissements touristiques et à la vérification de l'exécution des lois et règlements. Elle réunira également, en vue de son rapport, les notes, détails et renseignements précis dans des formes préparées par l'ONTRP, où figureront les informations recueillies au cours des inspections. L'ONTRP peut faire assister ses contrôleurs par des spécialistes dans les questions dont la connaissance et la vérification nécessitent une expérience technique et une spécialisation. Il peut, sur demande de son directeur, recourir à des autorités administratives ou techniques pour contrôler dans quelle mesure certaines décisions ou certaines dispositions des règlements et décrets ont été exécutées. Il peut également demander que soient arrêtées ou suspendues certaines poursuites, sur recommandation de la Commission consultative du Conseil National du Tourisme et conformément aux nécessités de l'intérêt touristique.\nArticle 65.- Le contrôle portera sur tous les établissements touristiques sans distinction.\nLes agents, sitôt le contrôle ordonné, se mettront en rapport avec le directeur responsable de l'établissement et devront produire, avant toute opération, leur carte d'identification, émanée de l'ONTRP, scellée et signée du Directeur Général ou de son représentant.\nArticle 66.- La Commission de contrôle ou l'agent contrôleur peut adresser des observations, même une mise en demeure à l'exploitant ou au directeur responsable, lorsqu'il sera constaté des changements non conformes à l'état de l'établissement, ou des infractions qui en diminuent le niveau.\nCes mises en demeure détermineront le genre d'irrégularités observées et le délai de sa réparation ou de sa cessation.\nProcès-verbal en sera dressé en triple original dont l'un sera remis au Directeur aux fins utiles, le deuxième, acheminé à la Section compétente de l'ONTRP et le troisième restera en la possession soit de la Commission, soit de l'agent contrôleur qui en a eu l'initiative. Ce procès-verbal mentionnera également les dires et observations de l'exploitant.\nArticle 67.- Un fichier sera tenu à l'ONTRP. Y figureront la carte de chaque établissement et son dossier où seront mentionnés les résultats de chaque inspection; les noms, prénoms des contrôleurs et les plaintes des visiteurs. L'établissement conservera un registre ou dossier comportant les mêmes mentions.\nArticle 68.- Toute commission ou agent chargé du contrôle prendra connaissance de ce dossier ou registre, notamment en ce qui concerne la dernière mise en demeure et le plus récent procès-verbal dressé, ce, avant d'entreprendre toute nouvelle inspection. Il sera procédé à la visite de l'établissement à la lumière de ces données et renseignements et de la situation présente.\nArticle 69.- S'agissant d'enquête ou de visite requise, la Commission de contrôle ou l'agent contrôleur doit soumettre au supérieur hiérarchique compétent un rapport succinct, circonstancié, comprenant les plaintes des visiteurs et les résultats de sa visite.\nLa commission ou l'agent de contrôle est tenu au secret de l'enquête et n'en communiquera le déroulement et les résultats qu'à la direction de la Section compétente.\nArticle 70.- En cas de récidive d'une infraction quelconque aux lois et règlements dûment constatée, les supérieurs compétents se réuniront et étudieront la situation de l'établissement. Il sera tenu compte dans cet examen de la marche générale des affaires de l'entreprise, du degré d'abaissement de son niveau et des fluctuations de sa conduite.\nUne nouvelle mise en demeure peut lui être notifiée pour une durée déterminée, si l'ONTRP le juge utile. Dans le cas contraire, l'ONTRP décidera la réduction de la classe et de la catégorie de l'établissement. En cas de renouvellement des infractions, si l'état disciplinaire, moral, sanitaire et professionnel de l'entreprise se détériore, l'ONTRP pourra ordonner la suspension temporaire de l'établissement ou, suivant la gravité du cas, la fermeture de l'établissement.\nChapitre X — Du retrait de la licence d'exploitation\nArticle 71.- En dehors du cas d'infractions, visé par l'article 70, la licence d'exploitation peut être retirée toutes les fois que l'établissement cesse définitivement ses activités. Cette mesure sera toujours précédée d'une injonction à l'intéressé de poursuivre le travail.\nAprès un délai de trois mois, à courir à partir de cette notification, s'il y a lieu à retrait, la Commission consultative du Conseil National du Tourisme devra toujours donner son avis.\nArticle 72.- Tout exploitant qui se propose de fermer son établissement ou d'en modifier son mode d'exploitation de façon permanente, est tenu d'informer l'ONTRP un mois avant la date fixée pour la fermeture ou la modification. L'ONTRP se réserve d'examiner les motifs de fermeture, ou des changements à apporter.\nChapitre XI — Dispositions diverses — Responsabilités\nArticle 73.- Les établissements touristiques demeurent soumis aux lois et règlements relatifs à la santé publique, à la Police générale, à la sécurité contre les risques d'incendie, de panique et d'accidents.\nDans ce domaine, la mission de l'ONTRP s'arrête au contrôle de la propreté de l'établissement et de ses employés et aux mesures à prendre après réception des rapports des susdits organismes.\nArticle 74.- Les questions du travail, notamment la protection des employés de ces établissements contre les accidents du travail et les maladies, resteront soumises aux lois et règlements en vigueur et relèvent du Département du Travail et des Affaires Sociales.\nArticle 75.- La direction des établissements touristiques est responsable des bagages et de l'argent qui lui sont confiés. Il en sera toujours délivré un reçu au déposant.\nLa direction assume la responsabilité de tout acte dû à sa faute ou à son défaut de surveillance. Elle répond de sa négligence et de celle de ses subordonnés.\nArticle 76.- En cas de survenance d'un décès, la direction de l'établissement doit sur-le-champ en informer le poste de police le plus proche ou se mettre en rapport avec le juge de paix du lieu qui apposera les scellés sur les ouvertures de la chambre.\nLa direction ne pourra délivrer les effets, bagages et autres, du défunt, qu'aux autorités compétentes ou à la personne dûment mandatée par elle à cet effet.\nArticle 77.- En cas d'épidémie, la direction de l'établissement doit immédiatement en informer les services compétents et prendre les mesures préliminaires en attendant l'action des organismes requis.\nArticle 78.- Les établissements touristiques doivent se garder de toute concurrence déloyale entre eux.\nSont considérés comme une concurrence déloyale, les actes accomplis par une entreprise contre une autre, par voie de provocation, d'allégations mensongères ou tous actes nuisibles commis au préjudice d'un autre établissement.\nChapitre XII — Des conditions propres à certains établissements\nArticle 79.- Pour bénéficier de la licence d'exploitation, émise par l'ONTRP, les propriétaires des entreprises énumérées au 3ème alinéa de l'article 1, devront adresser une requête à la direction de l'Office pour présenter leur projet. Elles y annexeront tous les renseignements nécessaires, notamment ceux relatifs à la spécialisation de leur exploitation et mettant en relief l'intérêt qu'offre leur projet pour la promotion du tourisme.\nOutre leur soumission au contrôle et aux suggestions de l'ONTRP, ainsi qu'aux obligations et responsabilités qui en découlent, ces établissements doivent réunir certaines conditions propres à leur spécialisation.\nArticle 80.- Les galeries d'art et maisons de vente d'articles pour touristes devront:\n1°) occuper un local propre, solide, sain ou pourvu d'installation électrique, d'accès facile donnant soit sur une rue, soit sur une route principale;\n2°) avoir un étalage bien ordonné pour faciliter le choix des acheteurs;\n3°) vendre des articles ou ouvrages sélectionnés, présentant un certain fini et sur lesquels seront affichés les prix en gourde ou en dollar;\n4°) avoir un personnel stylé et courtois, capable d'offrir le meilleur accueil aux visiteurs et de leur fournir les renseignements réclamés;\n5°) avoir dans le personnel au moins un membre qui parle deux langues: le français et l'anglais ou l'espagnol.\nArticle 81.- Les entreprises de transport ou de location de véhicules sont assujetties aux obligations supplémentaires suivantes:\n1°) indiquer, dans leur requête à l'ONTRP, le nombre de véhicules disponibles, leur état, leur marque;\n2°) les tenir dans un parfait état de propreté et d'équipement;\n3°) soumettre à l'Office une pièce comportant les numéros des cartes d'immatriculation, des polices d'assurances et des licences des chauffeurs ou bien des photocopies de ces pièces ainsi que tous documents attestant que ces voitures sont en bon état de fonctionnement et en parfait état d'usage;\n4°) afficher dans chaque voiture la liste des prix du transport arrêtée par l'ONTRP;\n5°) confier le véhicule à des chauffeurs expérimentés, stylés, courtois, et moraux;\n6°) s'agissant de location, observer le tarif fixé par l'ONTRP.\nArticle 82.- Les plages et stations balnéaires doivent être de vrais centres naturels d'héliothérapie et répondre aux conditions d'hygiène, de salubrité et de sécurité, particulièrement aux suivantes:\n1°) bien nettoyer le cadre ainsi que le fond de la mer;\n2°) pourvoir l'installation de toutes les attractions capables d'offrir aux estivants un séjour agréable: bars, canotage, etc.;\n3°) munir la station, en cas d'accidents, d'un service de sauvetage et de secours; la pourvoir d'appareils respiratoires;\n4°) délimiter le bain pour en faire une zone de protection balisée;\n5°) assurer le maintien de l'ordre à l'intérieur de la station;\n6°) afficher, à la porte principale ou au bar, les prix d'admission et de consommation.\nArticle 83.- Les conditions prévues aux articles 80, 81 et 82, seront toujours observées par l'exploitant ou la personne responsable de ces établissements, sous peine de voir retirer la licence d'exploitation selon la procédure tracée par l'article 70.",
 "structure": {
  "title": "Décret du 12 mars 1975 réglementant l'exploitation des établissements touristiques.",
  "annotationAuthor": "Édition Vandal",
  "navToc": [
   {
    "label": "Décret du 12 mars 1975 réglementant l'exploitation des établissements touristiqu",
    "anchor": "sec-1",
    "children": [
     {
      "label": "Chapitre premier — Définition et énumération",
      "anchor": "sec-1"
     },
     {
      "label": "Chapitre II — Des formalités préliminaires",
      "anchor": "sec-2"
     },
     {
      "label": "Chapitre III — De la licence d'exploitation",
      "anchor": "sec-3"
     },
     {
      "label": "Chapitre IV — Des avantages",
      "anchor": "sec-4"
     },
     {
      "label": "Chapitre V — Du fonctionnement",
      "anchor": "sec-5"
     },
     {
      "label": "Chapitre VI — Du classement et des prix — A.- Du classement",
      "anchor": "sec-6"
     },
     {
      "label": "Chapitre VII — Des conditions d'exploitation hôtelière",
      "anchor": "sec-7"
     },
     {
      "label": "Chapitre VIII — Des contrats hôteliers par intermédiaires ou agents de voyages",
      "anchor": "sec-8"
     },
     {
      "label": "Chapitre IX — Du contrôle des établissements touristiques",
      "anchor": "sec-9"
     },
     {
      "label": "Chapitre X — Du retrait de la licence d'exploitation",
      "anchor": "sec-10"
     },
     {
      "label": "Chapitre XI — Dispositions diverses — Responsabilités",
      "anchor": "sec-11"
     },
     {
      "label": "Chapitre XII — Des conditions propres à certains établissements",
      "anchor": "sec-12"
     }
    ]
   }
  ],
  "toc": [
   {
    "level": 4,
    "label": "Chapitre premier — Définition et énumération",
    "anchor": "sec-1",
    "kind": "chapitre"
   },
   {
    "level": 4,
    "label": "Chapitre II — Des formalités préliminaires",
    "anchor": "sec-2",
    "kind": "chapitre"
   },
   {
    "level": 4,
    "label": "Chapitre III — De la licence d'exploitation",
    "anchor": "sec-3",
    "kind": "chapitre"
   },
   {
    "level": 4,
    "label": "Chapitre IV — Des avantages",
    "anchor": "sec-4",
    "kind": "chapitre"
   },
   {
    "level": 4,
    "label": "Chapitre V — Du fonctionnement",
    "anchor": "sec-5",
    "kind": "chapitre"
   },
   {
    "level": 4,
    "label": "Chapitre VI — Du classement et des prix — A.- Du classement",
    "anchor": "sec-6",
    "kind": "chapitre"
   },
   {
    "level": 4,
    "label": "Chapitre VII — Des conditions d'exploitation hôtelière",
    "anchor": "sec-7",
    "kind": "chapitre"
   },
   {
    "level": 4,
    "label": "Chapitre VIII — Des contrats hôteliers par intermédiaires ou agents de voyages",
    "anchor": "sec-8",
    "kind": "chapitre"
   },
   {
    "level": 4,
    "label": "Chapitre IX — Du contrôle des établissements touristiques",
    "anchor": "sec-9",
    "kind": "chapitre"
   },
   {
    "level": 4,
    "label": "Chapitre X — Du retrait de la licence d'exploitation",
    "anchor": "sec-10",
    "kind": "chapitre"
   },
   {
    "level": 4,
    "label": "Chapitre XI — Dispositions diverses — Responsabilités",
    "anchor": "sec-11",
    "kind": "chapitre"
   },
   {
    "level": 4,
    "label": "Chapitre XII — Des conditions propres à certains établissements",
    "anchor": "sec-12",
    "kind": "chapitre"
   }
  ],
  "connexes": [],
  "jurisprudence": {},
  "commentaires": {},
  "connexe": {},
  "indexEntries": [],
  "oldVersions": {},
  "status": {},
  "labels": {
   "art-1": "Article 1er",
   "art-2": "Article 2",
   "art-3": "Article 3",
   "art-4": "Article 4",
   "art-5": "Article 5",
   "art-6": "Article 6",
   "art-7": "Article 7",
   "art-8": "Article 8",
   "art-9": "Article 9",
   "art-10": "Article 10",
   "art-11": "Article 11",
   "art-12": "Article 12",
   "art-13": "Article 13",
   "art-14": "Article 14",
   "art-15": "Article 15",
   "art-16": "Article 16",
   "art-17": "Article 17",
   "art-18": "Article 18",
   "art-19": "Article 19",
   "art-20": "Article 20",
   "art-21": "Article 21",
   "art-22": "Article 22",
   "art-23": "Article 23",
   "art-24": "Article 24",
   "art-25": "Article 25",
   "art-26": "Article 26",
   "art-27": "Article 27",
   "art-28": "Article 28",
   "art-29": "Article 29",
   "art-30": "Article 30",
   "art-31": "Article 31",
   "art-32": "Article 32",
   "art-33": "Article 33",
   "art-34": "Article 34",
   "art-35": "Article 35",
   "art-36": "Article 36",
   "art-37": "Article 37",
   "art-38": "Article 38",
   "art-39": "Article 39",
   "art-40": "Article 40",
   "art-41": "Article 41",
   "art-42": "Article 42",
   "art-43": "Article 43",
   "art-44": "Article 44",
   "art-45": "Article 45",
   "art-46": "Article 46",
   "art-47": "Article 47",
   "art-48": "Article 48",
   "art-49": "Article 49",
   "art-50": "Article 50",
   "art-51": "Article 51",
   "art-52": "Article 52",
   "art-53": "Article 53",
   "art-54": "Article 54",
   "art-55": "Article 55",
   "art-56": "Article 56",
   "art-57": "Article 57",
   "art-58": "Article 58",
   "art-59": "Article 59",
   "art-60": "Article 60",
   "art-61": "Article 61",
   "art-62": "Article 62",
   "art-63": "Article 63",
   "art-64": "Article 64",
   "art-65": "Article 65",
   "art-66": "Article 66",
   "art-67": "Article 67",
   "art-68": "Article 68",
   "art-69": "Article 69",
   "art-70": "Article 70",
   "art-71": "Article 71",
   "art-72": "Article 72",
   "art-73": "Article 73",
   "art-74": "Article 74",
   "art-75": "Article 75",
   "art-76": "Article 76",
   "art-77": "Article 77",
   "art-78": "Article 78",
   "art-79": "Article 79",
   "art-80": "Article 80",
   "art-81": "Article 81",
   "art-82": "Article 82",
   "art-83": "Article 83"
  },
  "crossRefs": []
 },
 "stats": {
  "paras": 196,
  "articles": 83,
  "toc": 12,
  "statuts": 0
 },
 "anomalies": []
}