{
 "id": "III-B-2",
 "partie": "III",
 "rubrique": "B",
 "title": "Convention de la Haye du 6 novembre 1925, concernant le dépôt international des dessins ou modèles industriels",
 "number": "Convention",
 "moniteurRef": null,
 "publicationDate": null,
 "body": "Ratifiée par décret de l'Assemblée Nationale en date du 27 août 1953 — Moniteur No 104 du 29 octobre 1953\nArticle 1er.- Les ressortissants de chacun des pays contractants, ainsi que les personnes ayant satisfait sur le territoire de l'Union restreinte aux conditions établies par l'article 3 de la Convention générale pourront s'assurer dans tous les autres pays contractants la protection de leurs dessins ou modèles industriels, au moyen d'un dépôt international effectué au Bureau international de la propriété industrielle à Berne.\nArticle 2.- Le dépôt international comprendra les dessins ou modèles soit sous la forme du produit auquel ils sont destinés, soit sous celle d'un dessin, d'une photographie ou de toute autre représentation graphique suffisante dudit dessin ou modèle.\nLes objets seront accompagnés d'une demande de dépôt international en double exemplaire contenant en langue française les indications que précisera le règlement d'exécution.\nArticle 3.- Aussitôt que le Bureau international de Berne aura reçu la demande de procéder à un dépôt international, il inscrira cette demande dans un registre spécial, notifiera cette inscription à l'administration qui lui aura été indiquée par chaque pays contractant et la publiera dans une feuille périodique, dont il distribuera gratuitement à chaque administration le nombre d'exemplaires voulu.\nLes dépôts seront conservés dans les archives du Bureau international.\nArticle 4.- Celui qui effectue le dépôt international d'un dessin ou modèle industriel est considéré jusqu'à preuve du contraire comme propriétaire de l'œuvre.\nLe dépôt international est purement déclaratif. En tant que dépôt, il produira dans chacun des pays contractants les mêmes effets que si les dessins ou modèles y avaient été directement déposés à la date du dépôt international, sous bénéfice toutefois des règles spéciales établies par le présent arrangement.\nLa publicité mentionnée dans l'article précédent sera considérée dans tous les pays contractants comme suffisante et aucune autre ne pourra être exigée du déposant sous réserve des formalités à remplir pour l'exercice du droit, conformément à la loi intérieure.\nLe droit de propriété établi par l'article 4 de la Convention générale sera garanti à tout dessin ou modèle qui a fait l'objet d'un dépôt international, sans obligations d'aucune des formalités prévues par ce même article.\nArticle 5.- Les pays contractants conviennent de ne pas exiger que les dessins ou modèles ayant fait l'objet d'un dépôt international soient revêtus d'une mention obligatoire. Ils ne les frapperont de déchéance ni pour défaut d'exploitation, ni pour introduction d'objets conformes à ceux protégés.\nArticle 6.- Le dépôt international peut comprendre, soit un seul dessin ou modèle, soit plusieurs, dont le nombre devra être précisé dans la demande.\nIl pourra être opéré, soit sous pli ouvert, soit sous pli cacheté. Seront acceptées notamment comme moyens de dépôt sous pli cacheté les enveloppes doubles, avec numéro de contrôle perforées (système Soleau) ou tout autre système approprié pour assurer l'identification.\nLes dimensions maxima des objets susceptibles d'être déposés seront déterminées par le règlement d'exécution.\nArticle 7.- La durée de la protection internationale est fixée à quinze ans, comptés à partir de la date du dépôt au Bureau international de Berne; ce délai est divisé en deux périodes, savoir une période de cinq ans et une période de dix ans.\nArticle 8.- Pendant la première période de protection, les dépôts seront admis, soit sous pli ouvert, soit sous pli cacheté; pendant la deuxième période ils ne seront admis qu'à découvert.\nArticle 9.- Au cours de la première période, les dépôts sous pli cachetés pourront être ouverts sur la demande du déposant ou d'un tribunal compétent; à l'expiration de la première période ils seront ouverts en vue du passage à la seconde période, sur une demande de prorogation.\nArticle 10.- Dans les six premiers mois de la cinquième année de la première période, le Bureau international donnera un avis officieux de l'échéance au déposant du dessin ou modèle.\nArticle 11.- Lorsque le déposant désirera obtenir la prolongation de la protection par le passage à la deuxième période, il devra remettre au Bureau international, au plus tard trois mois avant l'expiration du délai, une demande de prorogation.\nLe Bureau international procédera à l'ouverture du pli, s'il est cacheté, notifiera la prorogation intervenue à toutes les administrations et la publiera dans son journal.\nArticle 12.- Les dessins et modèles contenus dans les dépôts non prorogés, de même que ceux dont la protection est expirée, seront rendus tels quels à leurs propriétaires, sur leur demande et à leurs frais. S'ils ne sont pas réclamés, ils seront détruits au bout de deux ans.\nArticle 13.- Les déposants pourront à toute époque renoncer à leur dépôt, soit en totalité, soit partiellement, au moyen d'une déclaration qui sera adressée au Bureau international; ce dernier lui donnera la publicité prévue à l'article 3.\nLa renonciation comporte la restitution du dépôt aux frais du déposant.\nArticle 14.- Lorsqu'un tribunal ou toute autre autorité compétente ordonnera qu'un dessin ou modèle secret lui soit communiqué, le Bureau international, régulièrement requis, procédera à l'ouverture du paquet déposé, en extraira le dessin ou modèle demandé et le fera parvenir à l'autorité requérante. L'objet ainsi communiqué devra être restitué dans le plus bref délai possible et réincorporé dans le pli cacheté ou dans l'enveloppe.\nArticle 15.- Les taxes du dépôt international, qui seront à payer avant qu'il puisse être procédé à l'inscription du dépôt, sont ainsi fixées:\n1°) Pour un seul dessin ou modèle et pour la première période de cinq ans: une somme de 5 francs;\n2°) Pour un seul dessin ou modèle, à l'expiration de la première période et pour la durée de la deuxième période de dix ans: une somme de 10 francs;\n3°) Pour un dépôt multiple, à l'expiration de la première période et pour la durée de la deuxième période de dix ans: une somme de 50 francs.\nArticle 16.- Le produit net annuel des taxes sera réparti, conformément aux modalités prévues par l'article 8 du règlement, entre les pays contractants par les soins du Bureau international, après déduction des frais communs nécessités par l'exécution du présent arrangement.\nArticle 17.- Le Bureau international inscrira dans ses registres tous les changements affectant la propriété des dessins ou modèles, dont il aura reçu notification de la part des intéressés; il les dénoncera à son tour aux administrations des pays contractants et les publiera dans son journal.\nCes opérations peuvent être soumises à une taxe qui sera fixée par le règlement d'exécution.\nArticle 18.- Le Bureau international délivrera à toute personne, sur demande, contre une taxe fixée par le règlement, une expédition des mentions inscrites dans le registre au sujet d'un dessin ou modèle déterminé.\nL'expédition pourra être accompagnée d'un exemplaire ou d'une reproduction du dessin ou modèle, qui auront au Bureau international et qu'il certifiera conforme à l'objet déposé à découvert. Si le Bureau n'est pas en possession d'exemplaires ou de reproductions semblables, il en fera faire sur la demande des intéressés et à leurs frais.\nArticle 19.- Les archives du Bureau international, pour autant qu'elles contiennent des dépôts ouverts, sont accessibles au public. Toute personne peut en prendre connaissance, en présence d'un des fonctionnaires, ou obtenir du Bureau des renseignements écrits sur le contenu du registre, et cela moyennant paiement des taxes à fixer par le règlement.\nArticle 20.- Les détails d'application du présent arrangement seront déterminés par un règlement d'exécution dont les prescriptions pourront être, à toute époque, modifiées d'un commun accord par les administrations des pays contractants.\nArticle 21.- Les dispositions du présent Arrangement ne comportent qu'un minimum de protection; elles n'empêchent pas de revendiquer l'application des prescriptions plus larges qui seraient édictées par la législation intérieure d'un pays contractant; elles laissent également subsister l'application des dispositions de la Convention de Berne revisée de 1908, relatives à la protection des œuvres artistiques et des œuvres d'art appliquées à l'industrie.\nArticle 22.- Les pays membres de l'Union qui n'ont pas pris part au présent Arrangement, seront admis à y adhérer sur leur demande et dans la forme prescrite par les articles 16 et 16 bis de la Convention générale.\nArticle 23.- Le présent Arrangement sera ratifié et les ratifications en seront déposées à la Haye au plus tard le 1er mai 1928.\nIl entrera en vigueur, entre les pays qui l'auront ratifié, un mois après cette date et aura la même force et durée que la convention générale.\nEn foi de quoi, les plénipotentiaires des Etats ci-dessus énumérés ont signé le présent Arrangement.\nFait à la Haye, en un seul exemplaire, le 6 novembre 1925.",
 "structure": {
  "title": "Convention de la Haye du 6 novembre 1925, concernant le dépôt international des dessins ou modèles industriels",
  "annotationAuthor": "Édition Vandal",
  "navToc": [],
  "toc": [],
  "connexes": [],
  "jurisprudence": {},
  "commentaires": {},
  "connexe": {},
  "indexEntries": [],
  "oldVersions": {},
  "status": {},
  "labels": {
   "art-1": "Article 1er",
   "art-2": "Article 2",
   "art-3": "Article 3",
   "art-4": "Article 4",
   "art-5": "Article 5",
   "art-6": "Article 6",
   "art-7": "Article 7",
   "art-8": "Article 8",
   "art-9": "Article 9",
   "art-10": "Article 10",
   "art-11": "Article 11",
   "art-12": "Article 12",
   "art-13": "Article 13",
   "art-14": "Article 14",
   "art-15": "Article 15",
   "art-16": "Article 16",
   "art-17": "Article 17",
   "art-18": "Article 18",
   "art-19": "Article 19",
   "art-20": "Article 20",
   "art-21": "Article 21",
   "art-22": "Article 22",
   "art-23": "Article 23"
  },
  "crossRefs": []
 },
 "stats": {
  "paras": 42,
  "articles": 23,
  "toc": 0,
  "statuts": 0
 },
 "anomalies": []
}