{
 "id": "VII-A-2",
 "partie": "VII",
 "rubrique": "A",
 "title": "Décret du 26 septembre 1960 sur le livret de licence.",
 "number": "Décret du 26 septembre 1960",
 "moniteurRef": "Le Moniteur n° 86 du 26 septembre 1960",
 "publicationDate": "1960-09-26",
 "body": "…………………………………………………………………………………………\nArticle 2.- A partir de la publication du présent décret, cette taxe perçue par l'Administration Générale des Contributions suivant les modalités du décret-loi du 25 juillet 1941 dans son état actuel.\nArticle 3.- Le produit de ce droit sera déposé à un compte spécial à la Banque Nationale de la République d'Haïti et ne sera pas confondu avec la masse des recettes de l'Etat. Il servira à alimenter les fonds de garantie en vue de la libération des obligations de construction d'un aéroport telles que définies aux termes du contrat passé le 6 juillet 1960 entre les parties intéressées et sanctionné le 28 juillet de la même année.\n…………………………………………………………………………………………",
 "structure": {
  "title": "Décret du 26 septembre 1960 sur le livret de licence.",
  "annotationAuthor": "Édition Vandal",
  "navToc": [],
  "toc": [],
  "connexes": [],
  "jurisprudence": {},
  "commentaires": {},
  "connexe": {},
  "indexEntries": [],
  "oldVersions": {},
  "status": {},
  "labels": {
   "art-2": "Article 2",
   "art-3": "Article 3"
  },
  "crossRefs": []
 },
 "stats": {
  "paras": 6,
  "articles": 2,
  "toc": 0,
  "statuts": 0
 },
 "anomalies": []
}